iiitb_sd_fsm1.v
module iiitb_sd_fsm(sequence_in,clock,reset,detector_out);
input clock; // clock signal
input reset; // reset input
input sequence_in; // binary input
output reg detector_out; // output of the sequence detector
parameter  Zero=3'b000, // "Zero" State
  One=3'b001, // "One" State
  OneZero=3'b011, // "OneZero" State
  OneZeroOne=3'b010, // "OnceZeroOne" State
  OneZeroOneOne=3'b110,// "OneZeroOneOne" State
  OneZeroOneOneOne=3'b111;
reg [2:0] current_state, next_state; // current state and next state
// sequential memory of the Moore FSM
always @(posedge clock, posedge reset)
begin
 if(reset==1) 
 current_state <= Zero;// when reset=1, reset the state of the FSM to "Zero" State
 else
 current_state <= next_state; // otherwise, next state
end 
// combinational logic of the Moore FSM
// to determine next state 
always @(current_state,sequence_in)
begin
 case(current_state) 
 Zero:begin
  if(sequence_in==1)
   next_state = One;
  else
   next_state = Zero;
 end
 One:begin
  if(sequence_in==0)
   next_state = OneZero;
  else
   next_state = One;
 end
 OneZero:begin
  if(sequence_in==0)
   next_state = Zero;
  else
   next_state = OneZeroOne;
 end 
 OneZeroOne:begin
  if(sequence_in==0)
   next_state = OneZero;
  else
   next_state = OneZeroOneOne;
 end
 OneZeroOneOne:begin
  if(sequence_in==0)
   next_state = OneZero;
  else
   next_state = OneZeroOneOneOne;
 end
 OneZeroOneOneOne:begin
 if(sequence_in==1)
 next_state = One;
 else
 next_state=OneZero;
 end
 default:next_state = Zero;
 endcase
end
// combinational logic to determine the output
// of the Moore FSM, output only depends on current state
always @(current_state)
begin 
 case(current_state) 
 Zero:   detector_out = 0;
 One:   detector_out = 0;
 OneZero:  detector_out = 0;
 OneZeroOne:  detector_out = 0;
 OneZeroOneOne:  detector_out = 0;
 OneZeroOneOneOne:detector_out =1;
 default:  detector_out = 0;
 endcase
end 
endmodule

iiitb_sd_fsm1_tb.v
`timescale 1ns / 1ps
// fpga4student.com: FPGA projects, Verilog projects, VHDL projects
// Verilog project: Verilog code for Sequence Detector using Moore FSM
// Verilog Testbench for Sequence Detector using Moore FSM 
module iiitb_sd_fsm_tb;

 // Inputs
 reg sequence_in;
 reg clock;
 reg reset;

 // Outputs
 wire detector_out;

 // Instantiate the Sequence Detector using Moore FSM
 iiitb_sd_fsm uut (
  .sequence_in(sequence_in), 
  .clock(clock), 
  .reset(reset), 
  .detector_out(detector_out)
 );
 initial begin
 clock = 0;
  $dumpfile("sd_fsm.vcd");
 $dumpvars(0);
 forever #5 clock = ~clock;
 end 
 initial #200 $finish;  
 initial begin
  // Initialize Inputs
  sequence_in = 0;
  reset = 1;

  #10;reset = 0;
  
  #10;sequence_in = 1;
  #10; sequence_in = 0;
  #10; sequence_in = 1; 
  #10;sequence_in = 1; 
  #10;sequence_in = 1; 
  #10;sequence_in =0;
 
  // Add stimulus here

 end

endmodule

sd_fsm.vcd
$date
	Tue Aug 30 22:24:46 2022
$end
$version
	Icarus Verilog
$end
$timescale
	1ps
$end
$scope module iiitb_sd_fsm_tb $end
$var wire 1 ! detector_out $end
$var reg 1 " clock $end
$var reg 1 # reset $end
$var reg 1 $ sequence_in $end
$scope module uut $end
$var wire 1 " clock $end
$var wire 1 # reset $end
$var wire 1 $ sequence_in $end
$var reg 3 % current_state [2:0] $end
$var reg 1 ! detector_out $end
$var reg 3 & next_state [2:0] $end
$upscope $end
$upscope $end
$enddefinitions $end
#0
$dumpvars
b0 &
b0 %
0$
1#
0"
0!
$end
#5000
1"
#10000
0"
0#
#15000
1"
#20000
b1 &
0"
1$
#25000
b1 %
1"
#30000
b11 &
0"
0$
#35000
b0 &
b11 %
1"
#40000
b10 &
0"
1$
#45000
b110 &
b10 %
1"
#50000
0"
#55000
b111 &
b110 %
1"
#60000
0"
#65000
1!
b1 &
b111 %
1"
#70000
b11 &
0"
0$
#75000
0!
b0 &
b11 %
1"
#80000
0"
#85000
b0 %
1"
